MANIFEST.in
setup.py
pyradio/__init__.py
pyradio/log.py
pyradio/main.py
pyradio/player.py
pyradio/radio.py
pyradio/stations.csv
pyradio.egg-info/PKG-INFO
pyradio.egg-info/SOURCES.txt
pyradio.egg-info/dependency_links.txt
pyradio.egg-info/entry_points.txt
pyradio.egg-info/requires.txt
pyradio.egg-info/top_level.txt