Metadata-Version: 1.0
Name: pyradio
Version: 0.5.2
Summary: Command line internet radio player.
